{
  "DataList": [
    {
      "EventContentId": 846,
      "UniqueId": 100,
      "LocalizePrefabID": "UIPOPUP_MINIGAME_ROADPUZZLE_REWARD_RAIL_OPEN",
      "RewardParcelType": [
        "Currency"
      ],
      "RewardParcelId": [
        1
      ],
      "RewardParcelAmount": [
        5000
      ]
    },
    {
      "EventContentId": 10846,
      "UniqueId": 10100,
      "LocalizePrefabID": "UIPOPUP_MINIGAME_ROADPUZZLE_REWARD_RAIL_OPEN",
      "RewardParcelType": [
        "Currency"
      ],
      "RewardParcelId": [
        1
      ],
      "RewardParcelAmount": [
        7500
      ]
    }
  ]
}
