{
  "DataList": [
    {
      "EventContentId": 848,
      "CCGId": 848,
      "CostParcelType": "Item",
      "CostParcelId": 80650,
      "CostParcelAmount": 2000,
      "CardBackPath": "",
      "PerkCostParcelType": "Item",
      "PerkCostParcelId": 80654
    },
    {
      "EventContentId": 854,
      "CCGId": 854,
      "CostParcelType": "Item",
      "CostParcelId": 80757,
      "CostParcelAmount": 20,
      "CardBackPath": "",
      "PerkCostParcelType": "Item",
      "PerkCostParcelId": 80758
    }
  ]
}
